PyDiscoBot/__init__.py
PyDiscoBot/bot.py
PyDiscoBot/channels.py
PyDiscoBot/commands.py
PyDiscoBot/err.py
PyDiscoBot/pagination.py
PyDiscoBot/periodic_task.py
PyDiscoBot/.idea/.gitignore
PyDiscoBot/.idea/PyDiscoBot.iml
PyDiscoBot/.idea/material_theme_project_new.xml
PyDiscoBot/.idea/misc.xml
PyDiscoBot/.idea/modules.xml
PyDiscoBot/.idea/vcs.xml
PyDiscoBot/.idea/workspace.xml
PyDiscoBot/.idea/inspectionProfiles/profiles_settings.xml
pydiscobot-1.1.0.dist-info/METADATA
pydiscobot-1.1.0.dist-info/WHEEL
pydiscobot-1.1.0.dist-info/licenses/LICENSE
pydiscobot-1.1.0.dist-info/RECORD
