Metadata-Version: 2.3
Name: PyDiscoBot
Version: 1.1.0
Summary: A standard implimentation of discord-python API for bot usage.
Project-URL: Homepage, https://github.com/iroxusux/PyDiscoBot
Project-URL: Issues, https://github.com/iroxusux/PyDiscoBot/issues
Author-email: Brian LaFond <Brian.L.LaFond@gmail.com>
License: GNU GENERAL PUBLIC LICENSE
License-File: LICENSE
Keywords: api,bot,discord,python
Classifier: Development Status :: 4 - Beta
Classifier: Intended Audience :: Developers
Classifier: License :: OSI Approved :: GNU General Public License v3 (GPLv3)
Classifier: Programming Language :: Python :: 3.11
Classifier: Topic :: Software Development :: Build Tools
Requires-Python: >=3.11
Requires-Dist: discord-py
Requires-Dist: python-dotenv
